<?xml version="1.0" ?>
<tv>
  <channel>
    <name>TRT World TR</name>
    <id>TRTWorld.tr</id>
    <title>Storyteller</title>
    <desc>Tigre Gente follows a determined Bolivian park ranger and a Hong Kong journalist as they work to uncover the widespread jaguar trade in South America.</desc>
    <image>https://ankottvsc04.tvplus.com.tr:33207/CPS/images/universal/film/program/202509/20250909/10/2200272397035eb7f426_0_XL.jpg</image>
    <start>10:00AM</start>
    <finish>11:00AM</finish>
    <date>15 September 2025</date>
  </channel>
</tv>
