<?xml version="1.0" ?>
<tv>
  <channel>
    <name>ITV 1 UK</name>
    <id>ITV1.uk</id>
    <title>Dickinson's Real Deal</title>
    <desc>David Dickinson is at the National Motorcycle Museum in Solihull as one dealer ends up with the show's smallest profit to date and Mark Stevens is tempted by a tantalus.</desc>
    <image>https://images.metadata.sky.com/pd-image/97b59209-218c-3721-8432-9701b7a4f829/16-9</image>
    <start>02:00PM</start>
    <finish>03:00PM</finish>
    <date>16 September 2025</date>
  </channel>
</tv>
