<?xml version="1.0" ?>
<tv>
  <channel>
    <name>TVA CA</name>
    <title>Le masque de fer</title>
    <desc>Un voyageur anglais entreprend de cartographier l'Extr?me-Orient russe, ce qui donne lieu ? une incroyable aventure o? il rencontre des personnages plus grands que nature, dont Master et James Hook.</desc>
    <image>http://dshm.tmsimg.com/assets/p17755707_v_h8_ae.jpg</image>
    <start>04:35AM</start>
    <finish>06:51AM</finish>
    <date>11 May 2025</date>
  </channel>
  <channel>
    <name>TVA CA</name>
    <title>Silk Road</title>
    <desc>Ross Ulbricht cr?e Silk Road, le premier march? noir non r?glement? d'Internet. Lorsque le site web devient l'endroit r?v? pour la vente de drogues illicites, cela attire l'attention de Rick Bowden, un agent du DEA impr?visible qui tente d'arr?ter Ross par tous les moyens n?cessaires.</desc>
    <image>http://dshm.tmsimg.com/assets/p19254591_v_h8_aa.jpg</image>
    <start>06:51AM</start>
    <finish>08:55AM</finish>
    <date>11 May 2025</date>
  </channel>
  <channel>
    <name>TVA CA</name>
    <title>TVA nouvelles</title>
    <desc>Information r?gionale, nationale et internationale.</desc>
    <image>http://dshm.tmsimg.com/assets/p15219361_b_h8_af.jpg</image>
    <start>08:55AM</start>
    <finish>10:00AM</finish>
    <date>11 May 2025</date>
  </channel>
  <channel>
    <name>TVA CA</name>
    <title>Infopublicit?</title>
    <desc>Ceci est une ?mission publicitaire pay?e.</desc>
    <image>http://dshm.tmsimg.com/assets/p407792_b_h8_aa.jpg</image>
    <start>10:00AM</start>
    <finish>10:30AM</finish>
    <date>11 May 2025</date>
  </channel>
  <channel>
    <name>TVA CA</name>
    <title>La victoire de l'amour</title>
    <desc>Pr?sent?e par l'organisme catholique La Victoire de l'amour, cette ?mission religieuse du m?me nom est constitu?e de t?moignages de personnes qui sont parvenues, gr?ce ? leur foi, ? surmonter de lourdes ?preuves. Les invit?s font preuve de courage et sont une source d'inspiration.</desc>
    <image>http://dshm.tmsimg.com/assets/p16109298_b_h10_aa.jpg</image>
    <start>10:30AM</start>
    <finish>11:00AM</finish>
    <date>11 May 2025</date>
  </channel>
  <channel>
    <name>TVA CA</name>
    <title>Le Qu?bec matin week-end</title>
    <desc>Dans une ambiance d?contract?e, on reste au fait de l'actualit? et de tout ce qui se passe sur les sc?nes sportives et culturelles en compagnie de Marie-Lise Mormina, Simon Gamache-Fortin et Isabelle Perron.</desc>
    <image>http://dshm.tmsimg.com/assets/p10178759_b_h8_ad.jpg</image>
    <start>11:00AM</start>
    <finish>11:30AM</finish>
    <date>11 May 2025</date>
  </channel>
  <channel>
    <name>TVA CA</name>
    <title>Salut bonjour week-end</title>
    <desc>En provenance de Qu?bec, l'?quipe met l'accent sur l'actualit?, le culturel, la m?t?o, les sports, le Web et les diverses chroniques.</desc>
    <image>http://dshm.tmsimg.com/assets/p25694979_b_h8_aa.jpg</image>
    <start>11:30AM</start>
    <finish>03:30PM</finish>
    <date>11 May 2025</date>
  </channel>
  <channel>
    <name>TVA CA</name>
    <title>Apprendre ? t'aimer</title>
    <desc>Apprenant que son b?b? est trisomique, une jeune femme l'accepte sans r?serve, contrairement ? son conjoint sous le choc, qui refuse de s'en occuper.</desc>
    <image>http://dshm.tmsimg.com/assets/p22093779_v_h10_aa.jpg</image>
    <start>03:30PM</start>
    <finish>05:30PM</finish>
    <date>11 May 2025</date>
  </channel>
  <channel>
    <name>TVA CA</name>
    <title>La victoire de l'amour</title>
    <desc>Pr?sent?e par l'organisme catholique La Victoire de l'amour, cette ?mission religieuse du m?me nom est constitu?e de t?moignages de personnes qui sont parvenues, gr?ce ? leur foi, ? surmonter de lourdes ?preuves. Les invit?s font preuve de courage et sont une source d'inspiration.</desc>
    <image>http://dshm.tmsimg.com/assets/p16109298_b_h10_aa.jpg</image>
    <start>05:30PM</start>
    <finish>06:00PM</finish>
    <date>11 May 2025</date>
  </channel>
  <channel>
    <name>TVA CA</name>
    <title>Infopublicit?</title>
    <desc>Ceci est une ?mission publicitaire pay?e.</desc>
    <image>http://dshm.tmsimg.com/assets/p407792_b_h8_aa.jpg</image>
    <start>06:00PM</start>
    <finish>06:30PM</finish>
    <date>11 May 2025</date>
  </channel>
  <channel>
    <name>TVA CA</name>
    <title>Les looney tunes</title>
    <desc>Ces courts-m?trages Looney Tunes relatent les aventures de c?l?bres personnages tels que Bugs Bunny, Daffy Duck, Porky Pig, Elmer Fudd, Sylvestre (Grosminet), Titi, Marvin le Martien, Taz le diable de Tasmanie, Bip Bip et Coyote, Charlie le coq, Sam le pirate, P?p? le putois, Gossamer et bon nombre d'autres personnages.</desc>
    <image>http://dshm.tmsimg.com/assets/p24768210_b_h8_ac.jpg</image>
    <start>06:30PM</start>
    <finish>07:00PM</finish>
    <date>11 May 2025</date>
  </channel>
  <channel>
    <name>TVA CA</name>
    <title>La bagarre</title>
    <desc>Dans un monde o? les monstres sont apprivois?s et o? la lutte contre les monstres est un sport populaire, Winnie cherche ? suivre les traces de son p?re en tant que g?rant en transformant un monstre inexp?riment? en concurrent.</desc>
    <image>http://dshm.tmsimg.com/assets/p17870871_b_h8_ab.jpg</image>
    <start>07:00PM</start>
    <finish>08:49PM</finish>
    <date>11 May 2025</date>
  </channel>
  <channel>
    <name>TVA CA</name>
    <title>Le chemin du retour</title>
    <desc>Belle, une jeune fille de 12 ans ayant perdu sa m?re, peine ? surmonter une ?preuve. Atticus, son nouveau chiot, va am?liorer sa vie et celle de sa famille.</desc>
    <image>http://dshm.tmsimg.com/assets/p178110_v_h10_ac.jpg</image>
    <start>08:49PM</start>
    <finish>11:00PM</finish>
    <date>11 May 2025</date>
  </channel>
  <channel>
    <name>TVA CA</name>
    <title>TVA Nouvelles</title>
    <desc>On pr?sente l'actualit? de derni?re heure en temps r?el, les nouvelles r?gionales, internationales et ?conomiques, et plus encore. En provenance de Montr?al pour les stations des march?s de l'ouest du Qu?bec (Gatineau, Ottawa, Sherbrooke, Trois-Rivi?res et Rouyn-Noranda) et de Qu?bec pour les stations de l'est du Qu?bec (Rimouski, Rivi?re-du-Loup, Carleton sur Mer et Saguenay). On couvre toute l'actualit? qu?b?coise.</desc>
    <image>http://dshm.tmsimg.com/assets/p20941651_b_h8_af.jpg</image>
    <start>11:00PM</start>
    <finish>11:30PM</finish>
    <date>11 May 2025</date>
  </channel>
  <channel>
    <name>TVA CA</name>
    <title>La poule aux oeufs d'or</title>
    <desc>Six participants jouent ? l'une des trois parties, comprenant le jeu des roulettes, le jeu des portes et le fameux jeu de l'oeuf ou l'enveloppe; les participants sont tous assur?s de gagner un lot en argent et la chance de remporter le gros lot.</desc>
    <image>http://dshm.tmsimg.com/assets/p768466_b_h10_aa.jpg</image>
    <start>11:30PM</start>
    <finish>12:00AM</finish>
    <date>11 May 2025</date>
  </channel>
  <channel>
    <name>TVA CA</name>
    <title>Vlog</title>
    <desc>Pr?sentation des meilleures vid?os trouv?es sur le web.</desc>
    <image>http://dshm.tmsimg.com/assets/p311703_b_h8_aa.jpg</image>
    <start>12:00AM</start>
    <finish>12:30AM</finish>
    <date>12 May 2025</date>
  </channel>
  <channel>
    <name>TVA CA</name>
    <title>Sortez-moi d'ici!</title>
    <desc>Brigitte affronte le premier d?fi ?toile individuel de la saison; un d?fi ? la plage confronte Jean-Michel et Jeff; au gala, apr?s avoir revisit? les souvenirs de Guy et Rosalie, les campeurs sont contraints de laisser partir l'un des leurs.</desc>
    <image>http://dshm.tmsimg.com/assets/p23894397_b_h8_ac.jpg</image>
    <start>12:30AM</start>
    <finish>02:00AM</finish>
    <date>12 May 2025</date>
  </channel>
  <channel>
    <name>TVA CA</name>
    <title>Jean-Marc Parent: utopie</title>
    <desc>Apr?s 35 ans de carri?re, l'humoriste Jean-Marc Parent est plus que jamais d?termin? et plein d'?nergie pour partager sa vision utopique du monde.</desc>
    <image>http://dshm.tmsimg.com/assets/p26551110_b_h8_aa.jpg</image>
    <start>02:00AM</start>
    <finish>03:00AM</finish>
    <date>12 May 2025</date>
  </channel>
  <channel>
    <name>TVA CA</name>
    <title>TVA Nouvelles</title>
    <desc>On pr?sente l'actualit? de derni?re heure en temps r?el, les nouvelles r?gionales, internationales et ?conomiques, et plus encore. En provenance de Montr?al pour les stations des march?s de l'ouest du Qu?bec (Gatineau, Ottawa, Sherbrooke, Trois-Rivi?res et Rouyn-Noranda) et de Qu?bec pour les stations de l'est du Qu?bec (Rimouski, Rivi?re-du-Loup, Carleton sur Mer et Saguenay). On couvre toute l'actualit? qu?b?coise.</desc>
    <image>http://dshm.tmsimg.com/assets/p20941651_b_h8_af.jpg</image>
    <start>03:00AM</start>
    <finish>03:30AM</finish>
    <date>12 May 2025</date>
  </channel>
  <channel>
    <name>TVA CA</name>
    <title>QG</title>
    <desc>Possiblement mortel, on tente de comprendre les causes d'un accident survenu en d?but de nuit; l'entrevue avec le conducteur du v?hicule impliqu? sera d?cisive pour conclure l'enqu?te; on cherche un homme intoxiqu? sur la voie publique.</desc>
    <image>http://dshm.tmsimg.com/assets/p23614730_b_h8_aa.jpg</image>
    <start>03:30AM</start>
    <finish>04:04AM</finish>
    <date>12 May 2025</date>
  </channel>
  <channel>
    <name>TVA CA</name>
    <title>La f?te des M?res</title>
    <desc>M?re c?libataire de deux gar?ons, Sandy a d? mal ? accepter que son ex-mari soit refait sa vie avec une femme beaucoup plus jeune que lui. De son c?t? Jesse, une amie de Sandy, ne se souvient plus de l'origine de sa dispute avec sa m?re. Alors qu'elles ne se sont pas parl? depuis des mois, cette derni?re arrive sans pr?venir. De son c?t?, la jeune Britt voudrait comprendre pourquoi sa m?re l'a abandonn?e. Elle d?couvre son identit?.</desc>
    <image>http://dshm.tmsimg.com/assets/p12283042_v_h8_ao.jpg</image>
    <start>04:04AM</start>
    <finish>06:28AM</finish>
    <date>12 May 2025</date>
  </channel>
  <channel>
    <name>TVA CA</name>
    <title>Tout va bien</title>
    <desc>Huit mois apr?s la mort de son ?pouse, Franck Goode souhaite se r?unir avec ses quatre enfants devenus adultes. Quand ils annulent leur visite ? la derni?re minute, Franck, contre l'avis de son m?decin, entreprend un voyage pour reprendre contact avec sa prog?niture. Alors qu'il leur rend visite ? tour de r?le, Franck s'aper?oit que la vie de ses enfants est loin d'?tre parfaite.</desc>
    <image>http://dshm.tmsimg.com/assets/p3502545_v_h10_aw.jpg</image>
    <start>06:28AM</start>
    <finish>08:30AM</finish>
    <date>12 May 2025</date>
  </channel>
  <channel>
    <name>TVA CA</name>
    <title>Infopublicit?</title>
    <desc>Ceci est une ?mission publicitaire pay?e.</desc>
    <image>http://dshm.tmsimg.com/assets/p407792_b_h8_aa.jpg</image>
    <start>08:30AM</start>
    <finish>09:00AM</finish>
    <date>12 May 2025</date>
  </channel>
  <channel>
    <name>TVA CA</name>
    <title>Infopublicit?</title>
    <desc>Ceci est une ?mission publicitaire pay?e.</desc>
    <image>http://dshm.tmsimg.com/assets/p407792_b_h8_aa.jpg</image>
    <start>09:00AM</start>
    <finish>09:30AM</finish>
    <date>12 May 2025</date>
  </channel>
  <channel>
    <name>TVA CA</name>
    <title>TVA nouvelles</title>
    <desc>Information r?gionale, nationale et internationale.</desc>
    <image>http://dshm.tmsimg.com/assets/p15219361_b_h8_af.jpg</image>
    <start>09:30AM</start>
    <finish>10:00AM</finish>
    <date>12 May 2025</date>
  </channel>
  <channel>
    <name>TVA CA</name>
    <title>La victoire de l'amour</title>
    <desc>Pr?sent?e par l'organisme catholique La Victoire de l'amour, cette ?mission religieuse du m?me nom est constitu?e de t?moignages de personnes qui sont parvenues, gr?ce ? leur foi, ? surmonter de lourdes ?preuves. Les invit?s font preuve de courage et sont une source d'inspiration.</desc>
    <image>http://dshm.tmsimg.com/assets/p16109298_b_h10_aa.jpg</image>
    <start>10:00AM</start>
    <finish>10:15AM</finish>
    <date>12 May 2025</date>
  </channel>
  <channel>
    <name>TVA CA</name>
    <title>La victoire de l'amour</title>
    <desc>Pr?sent?e par l'organisme catholique La Victoire de l'amour, cette ?mission religieuse du m?me nom est constitu?e de t?moignages de personnes qui sont parvenues, gr?ce ? leur foi, ? surmonter de lourdes ?preuves. Les invit?s font preuve de courage et sont une source d'inspiration.</desc>
    <image>http://dshm.tmsimg.com/assets/p16109298_b_h10_aa.jpg</image>
    <start>10:15AM</start>
    <finish>10:30AM</finish>
    <date>12 May 2025</date>
  </channel>
  <channel>
    <name>TVA CA</name>
    <title>Le Qu?bec matin</title>
    <desc>On reste ? l'aff?t de toute l'actualit? sur des sujets tels que la politique, l'?conomie, la sant?, la m?t?o et la consommation gr?ce ? des reporters en direct sur le terrain ? Montr?al, Qu?bec, Sherbrooke, Trois-Rivi?res, Saguenay et Rimouski.</desc>
    <image>http://dshm.tmsimg.com/assets/p11006847_b_h8_aa.jpg</image>
    <start>10:30AM</start>
    <finish>11:30AM</finish>
    <date>12 May 2025</date>
  </channel>
  <channel>
    <name>TVA CA</name>
    <title>Salut bonjour</title>
    <desc>Actualit?, revue de presse, m?t?o, circulation, actualit?s culturelles et sportives sont abord?es avec dynamisme et enthousiasme chaque matin. Diff?rents collaborateurs viennent partager leurs passions: cuisine, sant?, famille, mode, etc.</desc>
    <image>http://dshm.tmsimg.com/assets/p890919_b_h8_ab.jpg</image>
    <start>11:30AM</start>
    <finish>03:29PM</finish>
    <date>12 May 2025</date>
  </channel>
  <channel>
    <name>TVA CA</name>
    <title>Le tricheur</title>
    <desc>Rosalie Vaillancourt, Gino Chouinard, Jeff Boudreau, Brigitte Lafleur, Sonia Vachon.</desc>
    <image>http://dshm.tmsimg.com/assets/p28151111_b_h8_aa.jpg</image>
    <start>03:29PM</start>
    <finish>03:59PM</finish>
    <date>12 May 2025</date>
  </channel>
  <channel>
    <name>TVA CA</name>
    <title>Mario Dumont</title>
    <desc>Mario Dumont d?cortique les grands titres de l'actualit? et s'int?resse ? ce qui touche les Qu?b?cois, tels que la sant?, les finances personnelles et les nouvelles politiques.</desc>
    <image>http://dshm.tmsimg.com/assets/p9426305_b_h8_ad.jpg</image>
    <start>03:59PM</start>
    <finish>04:58PM</finish>
    <date>12 May 2025</date>
  </channel>
  <channel>
    <name>TVA CA</name>
    <title>TVA nouvelles</title>
    <desc>Avec Julie Marcoux, on reste au fait des nouvelles de derni?re heure, des analyses, du sport et la m?t?o dans un bulletin d'information complet.</desc>
    <image>http://dshm.tmsimg.com/assets/p9490084_b_h8_af.jpg</image>
    <start>04:58PM</start>
    <finish>06:00PM</finish>
    <date>12 May 2025</date>
  </channel>
  <channel>
    <name>TVA CA</name>
    <title>Bernadette a disparu</title>
    <desc>Bernadette Fox est une femme de Seattle qui a tout, y compris un mari attentionn? et une fille brillante. Lorsqu'elle dispara?t de fa?on inattendue, son mari et sa fille se lancent dans une aventure passionnante pour r?soudre le myst?re de sa disparition.</desc>
    <image>http://dshm.tmsimg.com/assets/p15144835_v_h8_aj.jpg</image>
    <start>06:00PM</start>
    <finish>08:00PM</finish>
    <date>12 May 2025</date>
  </channel>
  <channel>
    <name>TVA CA</name>
    <title>Infopublicit?</title>
    <desc>Ceci est une ?mission publicitaire pay?e.</desc>
    <image>http://dshm.tmsimg.com/assets/p407792_b_h8_aa.jpg</image>
    <start>08:00PM</start>
    <finish>08:30PM</finish>
    <date>12 May 2025</date>
  </channel>
  <channel>
    <name>TVA CA</name>
    <title>Les feux de l'amour</title>
    <desc>Jack fait une offre ? Dina; Chloe riposte; Billy et Phyllis font un grand pas dans leur relation.</desc>
    <image>http://dshm.tmsimg.com/assets/p183904_b_h10_ak.jpg</image>
    <start>08:30PM</start>
    <finish>09:28PM</finish>
    <date>12 May 2025</date>
  </channel>
  <channel>
    <name>TVA CA</name>
    <title>Top mod?les</title>
    <desc>Poppy et Luna appr?cient le c?t? raffin? de leur appartenance ? la famille Spencer; le sac ? dos de Tom est retrouv? dans un placard de rangement ? Il Giardino.</desc>
    <image>http://dshm.tmsimg.com/assets/p183907_b_h10_ab.jpg</image>
    <start>09:28PM</start>
    <finish>09:58PM</finish>
    <date>12 May 2025</date>
  </channel>
  <channel>
    <name>TVA CA</name>
    <title>TVA nouvelles</title>
    <desc>Avec Sophie Thibault, on est au fait des nouvelles de derni?re heure, des analyses, du sport et de la m?t?o au bulletin d'information compl?te et pr?f?r? des Qu?b?cois.</desc>
    <image>http://dshm.tmsimg.com/assets/p9490107_b_h8_ae.jpg</image>
    <start>09:58PM</start>
    <finish>10:58PM</finish>
    <date>12 May 2025</date>
  </channel>
  <channel>
    <name>TVA CA</name>
    <title>TVA nouvelles</title>
    <desc>Avec Sophie Thibault, on est au fait des nouvelles de derni?re heure, des analyses, du sport et de la m?t?o au bulletin d'information compl?te et pr?f?r? des Qu?b?cois.</desc>
    <image>http://dshm.tmsimg.com/assets/p9490107_b_h8_ae.jpg</image>
    <start>10:58PM</start>
    <finish>11:29PM</finish>
    <date>12 May 2025</date>
  </channel>
  <channel>
    <name>TVA CA</name>
    <title>Le tricheur</title>
    <desc>Anne Grenier, Alain Dumas, F?lix-Antoine Tremblay, Dave Morissette, Anick Dumontet.</desc>
    <image>http://dshm.tmsimg.com/assets/p9000285_b_h8_aa.jpg</image>
    <start>11:29PM</start>
    <finish>11:59PM</finish>
    <date>12 May 2025</date>
  </channel>
  <channel>
    <name>TVA CA</name>
    <title>Masterchef Junior Qu?bec</title>
    <desc>Les candidats assistent ? une d?monstration culinaire impressionnante d'un chef de talent; avant de partir, il leur laisse un cadeau: des nouilles fra?ches fa?onn?es ? la main; ils devront les mettre en valeur dans un plat aux saveurs asiatiques.</desc>
    <image>http://dshm.tmsimg.com/assets/p29920130_b_h8_ab.jpg</image>
    <start>11:59PM</start>
    <finish>12:30AM</finish>
    <date>12 May 2025</date>
  </channel>
  <channel>
    <name>TVA CA</name>
    <title>Un zoo pas comme les autres</title>
    <desc>Cliff doit faire face ? Ricco la grue royale pour transf?rer des cygnes r?barbatifs; ?milie confie Marco l'alpaga ? sa famille adoptive qui pourra mieux r?pondre ? ses besoins particuliers; Val?rie nourrit les coatis ? la suite d'une m?saventure.</desc>
    <image>http://dshm.tmsimg.com/assets/p16356256_b_h8_ah.jpg</image>
    <start>12:30AM</start>
    <finish>01:00AM</finish>
    <date>13 May 2025</date>
  </channel>
  <channel>
    <name>TVA CA</name>
    <title>Si on s'aimait c?l?brit?s</title>
    <desc>On suit quatre personnalit?s qui souhaitent vivre une exp?rience relationnelle unique.</desc>
    <image>http://dshm.tmsimg.com/assets/p29635638_b_h8_ab.jpg</image>
    <start>01:00AM</start>
    <finish>02:00AM</finish>
    <date>13 May 2025</date>
  </channel>
  <channel>
    <name>TVA CA</name>
    <title>La recrue</title>
    <desc>La lune de miel de Nolan et Bailey tourne au cauchemar; un meurtre a ?t? commis sur l'?le o? ils s?journent, et il s'agit de leur femme de m?nage; pendant ce temps, Tim et Celina font ?quipe pour d?couvrir l'identit? d'un voleur amn?sique.</desc>
    <image>http://dshm.tmsimg.com/assets/p15523389_b_h8_ax.jpg</image>
    <start>02:00AM</start>
    <finish>03:00AM</finish>
    <date>13 May 2025</date>
  </channel>
  <channel>
    <name>TVA CA</name>
    <title>TVA nouvelles</title>
    <desc>On pr?sente l'actualit? de derni?re heure en temps r?el, les nouvelles r?gionales, internationales et ?conomiques, et plus encore.</desc>
    <image>http://dshm.tmsimg.com/assets/p7842532_b_h8_aa.jpg</image>
    <start>03:00AM</start>
    <finish>03:35AM</finish>
    <date>13 May 2025</date>
  </channel>
  <channel>
    <name>TVA CA</name>
    <title>? vos affaires</title>
    <desc>Simon Philibert d?cortique l'actualit? ?conomique et ses impacts dans le quotidien des Qu?b?cois.</desc>
    <image>http://dshm.tmsimg.com/assets/p19324420_b_h8_ab.jpg</image>
    <start>03:35AM</start>
    <finish>04:05AM</finish>
    <date>13 May 2025</date>
  </channel>
  <channel>
    <name>TVA CA</name>
    <title>Premi?res vacances</title>
    <desc>Marion et Ben, trentenaires, font connaissance sur Tinder. C'est ? peu pr?s tout ce qu'ils ont en commun. Cependant, ils d?cident tout de m?me, au petit matin de leur rencontre, de partir ensemble en vacances.</desc>
    <image>http://dshm.tmsimg.com/assets/p16978868_v_h8_ag.jpg</image>
    <start>04:05AM</start>
    <finish>06:10AM</finish>
    <date>13 May 2025</date>
  </channel>
  <channel>
    <name>TVA CA</name>
    <title>Desperate Riders</title>
    <desc>Apr?s avoir sauv? le jeune Billy d'une fusillade, Kansas Red est sollicit? par le gar?on pour une aide suppl?mentaire. Il doit lib?rer la m?re de Billy, Carol, qui a ?t? enlev? auparavant par un hors-la-loi Thorn. Un peu plus tard, Leslie, la belle h?ro?ne au revolver, les rejoints, elle aussi d?sireuse de r?gler ses comptes avec Thorn.</desc>
    <image>http://dshm.tmsimg.com/assets/p21020879_v_h8_aa.jpg</image>
    <start>06:10AM</start>
    <finish>07:47AM</finish>
    <date>13 May 2025</date>
  </channel>
  <channel>
    <name>TVA CA</name>
    <title>Infopublicit?</title>
    <desc>Ceci est une ?mission publicitaire pay?e.</desc>
    <image>http://dshm.tmsimg.com/assets/p407792_b_h8_aa.jpg</image>
    <start>07:47AM</start>
    <finish>08:17AM</finish>
    <date>13 May 2025</date>
  </channel>
  <channel>
    <name>TVA CA</name>
    <title>Infopublicit?</title>
    <desc>Ceci est une ?mission publicitaire pay?e.</desc>
    <image>http://dshm.tmsimg.com/assets/p407792_b_h8_aa.jpg</image>
    <start>08:17AM</start>
    <finish>08:47AM</finish>
    <date>13 May 2025</date>
  </channel>
  <channel>
    <name>TVA CA</name>
    <title>Infopublicit?</title>
    <desc>Ceci est une ?mission publicitaire pay?e.</desc>
    <image>http://dshm.tmsimg.com/assets/p407792_b_h8_aa.jpg</image>
    <start>08:47AM</start>
    <finish>09:17AM</finish>
    <date>13 May 2025</date>
  </channel>
  <channel>
    <name>TVA CA</name>
    <title>TVA nouvelles</title>
    <desc>Information r?gionale, nationale et internationale.</desc>
    <image>http://dshm.tmsimg.com/assets/p15219361_b_h8_af.jpg</image>
    <start>09:17AM</start>
    <finish>10:00AM</finish>
    <date>13 May 2025</date>
  </channel>
  <channel>
    <name>TVA CA</name>
    <title>La victoire de l'amour</title>
    <desc>Pr?sent?e par l'organisme catholique La Victoire de l'amour, cette ?mission religieuse du m?me nom est constitu?e de t?moignages de personnes qui sont parvenues, gr?ce ? leur foi, ? surmonter de lourdes ?preuves. Les invit?s font preuve de courage et sont une source d'inspiration.</desc>
    <image>http://dshm.tmsimg.com/assets/p16109298_b_h10_aa.jpg</image>
    <start>10:00AM</start>
    <finish>10:15AM</finish>
    <date>13 May 2025</date>
  </channel>
  <channel>
    <name>TVA CA</name>
    <title>La victoire de l'amour</title>
    <desc>Pr?sent?e par l'organisme catholique La Victoire de l'amour, cette ?mission religieuse du m?me nom est constitu?e de t?moignages de personnes qui sont parvenues, gr?ce ? leur foi, ? surmonter de lourdes ?preuves. Les invit?s font preuve de courage et sont une source d'inspiration.</desc>
    <image>http://dshm.tmsimg.com/assets/p16109298_b_h10_aa.jpg</image>
    <start>10:15AM</start>
    <finish>10:30AM</finish>
    <date>13 May 2025</date>
  </channel>
  <channel>
    <name>TVA CA</name>
    <title>Le Qu?bec matin</title>
    <desc>On reste ? l'aff?t de toute l'actualit? sur des sujets tels que la politique, l'?conomie, la sant?, la m?t?o et la consommation gr?ce ? des reporters en direct sur le terrain ? Montr?al, Qu?bec, Sherbrooke, Trois-Rivi?res, Saguenay et Rimouski.</desc>
    <image>http://dshm.tmsimg.com/assets/p11006847_b_h8_aa.jpg</image>
    <start>10:30AM</start>
    <finish>11:30AM</finish>
    <date>13 May 2025</date>
  </channel>
  <channel>
    <name>TVA CA</name>
    <title>Salut bonjour</title>
    <desc>Actualit?, revue de presse, m?t?o, circulation, actualit?s culturelles et sportives sont abord?es avec dynamisme et enthousiasme chaque matin. Diff?rents collaborateurs viennent partager leurs passions: cuisine, sant?, famille, mode, etc.</desc>
    <image>http://dshm.tmsimg.com/assets/p890919_b_h8_ab.jpg</image>
    <start>11:30AM</start>
    <finish>03:29PM</finish>
    <date>13 May 2025</date>
  </channel>
  <channel>
    <name>TVA CA</name>
    <title>Le tricheur</title>
    <desc>Rosalie Vaillancourt, Gino Chouinard, Jeff Boudreau, Brigitte Lafleur, Sonia Vachon.</desc>
    <image>http://dshm.tmsimg.com/assets/p9000285_b_h8_aa.jpg</image>
    <start>03:29PM</start>
    <finish>03:59PM</finish>
    <date>13 May 2025</date>
  </channel>
  <channel>
    <name>TVA CA</name>
    <title>Mario Dumont</title>
    <desc>Mario Dumont d?cortique les grands titres de l'actualit? et s'int?resse ? ce qui touche les Qu?b?cois, tels que la sant?, les finances personnelles et les nouvelles politiques.</desc>
    <image>http://dshm.tmsimg.com/assets/p28151183_b_h8_aa.jpg</image>
    <start>03:59PM</start>
    <finish>04:58PM</finish>
    <date>13 May 2025</date>
  </channel>
  <channel>
    <name>TVA CA</name>
    <title>TVA nouvelles</title>
    <desc>Avec Julie Marcoux, on reste au fait des nouvelles de derni?re heure, des analyses, du sport et la m?t?o dans un bulletin d'information complet.</desc>
    <image>http://dshm.tmsimg.com/assets/p9490084_b_h8_af.jpg</image>
    <start>04:58PM</start>
    <finish>06:00PM</finish>
    <date>13 May 2025</date>
  </channel>
  <channel>
    <name>TVA CA</name>
    <title>Stan et Ollie</title>
    <desc>Laurel et Hardy - la plus grande ?quipe de com?diens au monde - sont confront?s ? un avenir incertain, leur ?ges d'or des films hollywoodiens sont derri?re eux. R?duit par l'?ge, le duo a d?cid? de renouer avec ses admirateurs en faisant des spectacles en Grande-Bretagne en 1953. Ils deviennent un succ?s instantan?, mais Stan et Ollie ne peuvent pas vraiment oublier le pass? tant la tension enfouie et la sant? d?faillante de Hardy commencer ? menacer leur pr?cieux groupe.</desc>
    <image>http://dshm.tmsimg.com/assets/p16108758_b_h10_ad.jpg</image>
    <start>06:00PM</start>
    <finish>08:00PM</finish>
    <date>13 May 2025</date>
  </channel>
  <channel>
    <name>TVA CA</name>
    <title>Infopublicit?</title>
    <desc>Ceci est une ?mission publicitaire pay?e.</desc>
    <image>http://dshm.tmsimg.com/assets/p407792_b_h8_aa.jpg</image>
    <start>08:00PM</start>
    <finish>08:30PM</finish>
    <date>13 May 2025</date>
  </channel>
  <channel>
    <name>TVA CA</name>
    <title>Les feux de l'amour</title>
    <desc>Neil craint que sa famille ne soit d?chir?e; Reed se dispute avec Charlie; Victoria refuse de s'installer avec Juliet.</desc>
    <image>http://dshm.tmsimg.com/assets/p183904_b_h10_ak.jpg</image>
    <start>08:30PM</start>
    <finish>09:28PM</finish>
    <date>13 May 2025</date>
  </channel>
  <channel>
    <name>TVA CA</name>
    <title>Top mod?les</title>
    <desc>Jack et Li cachent ? Finn des informations sur la nuit du concert de Tom; Bill offre ? Luna un cadeau extraordinaire; le contenu choquant du sac ? dos de Tom est r?v?l?.</desc>
    <image>http://dshm.tmsimg.com/assets/p183907_b_h10_ab.jpg</image>
    <start>09:28PM</start>
    <finish>09:58PM</finish>
    <date>13 May 2025</date>
  </channel>
  <channel>
    <name>TVA CA</name>
    <title>TVA nouvelles</title>
    <desc>Avec Sophie Thibault, on est au fait des nouvelles de derni?re heure, des analyses, du sport et de la m?t?o au bulletin d'information compl?te et pr?f?r? des Qu?b?cois.</desc>
    <image>http://dshm.tmsimg.com/assets/p9490107_b_h8_ae.jpg</image>
    <start>09:58PM</start>
    <finish>10:58PM</finish>
    <date>13 May 2025</date>
  </channel>
  <channel>
    <name>TVA CA</name>
    <title>TVA nouvelles</title>
    <desc>Avec Sophie Thibault, on est au fait des nouvelles de derni?re heure, des analyses, du sport et de la m?t?o au bulletin d'information compl?te et pr?f?r? des Qu?b?cois.</desc>
    <image>http://dshm.tmsimg.com/assets/p9490107_b_h8_ae.jpg</image>
    <start>10:58PM</start>
    <finish>11:29PM</finish>
    <date>13 May 2025</date>
  </channel>
  <channel>
    <name>TVA CA</name>
    <title>Le tricheur</title>
    <desc>Anne Grenier, Alain Dumas, F?lix-Antoine Tremblay, Dave Morissette, Anick Dumontet.</desc>
    <image>http://dshm.tmsimg.com/assets/p9000285_b_h8_aa.jpg</image>
    <start>11:29PM</start>
    <finish>11:59PM</finish>
    <date>13 May 2025</date>
  </channel>
  <channel>
    <name>TVA CA</name>
    <title>Masterchef Junior Qu?bec</title>
    <desc>Les juges proposent aux candidats un d?fi o? ils auront ? voyager autour du monde; les concurrents doivent choisir une destination et s'en inspirer pour cuisiner un plat gastronomique en duos; une ?quipe poss?de toutefois un avantage important.</desc>
    <image>http://dshm.tmsimg.com/assets/p29920131_b_h8_ab.jpg</image>
    <start>11:59PM</start>
    <finish>12:30AM</finish>
    <date>13 May 2025</date>
  </channel>
  <channel>
    <name>TVA CA</name>
    <title>Planter avec Marthe</title>
    <desc>Marthe vole au secours de Sonia, dont le terrain s'est transform? en jungle incontr?lable; des arbres en d?tresse, des plantes rebelles et une artiste en mode survie v?g?tale; Marthe passe ? l'action; elle initie Sonia ? l'art du bonsa?.</desc>
    <image>http://dshm.tmsimg.com/assets/p27537162_b_h8_aa.jpg</image>
    <start>12:30AM</start>
    <finish>01:00AM</finish>
    <date>14 May 2025</date>
  </channel>
  <channel>
    <name>TVA CA</name>
    <title>9-1-1</title>
    <desc>Maddie et Athena enqu?tent sur l'enl?vement d'une m?re et de son b?b?; pendant ce temps, Hen et Karen font une importante d?couverte sur la famille de Mara; enfin, Eddie est aux prises avec des sentiments non r?solus pour une personne de son pass?.</desc>
    <image>http://dshm.tmsimg.com/assets/p14154513_b_h8_bc.jpg</image>
    <start>01:00AM</start>
    <finish>02:00AM</finish>
    <date>14 May 2025</date>
  </channel>
  <channel>
    <name>TVA CA</name>
    <title>Famille de criminel</title>
    <desc>Parce qu'il ne veut pas suivre les r?gles, le trafiquant Ga?tan S?vigny est assassin?.</desc>
    <image>http://dshm.tmsimg.com/assets/p25697405_b_h8_ab.jpg</image>
    <start>02:00AM</start>
    <finish>03:00AM</finish>
    <date>14 May 2025</date>
  </channel>
  <channel>
    <name>TVA CA</name>
    <title>TVA nouvelles</title>
    <desc>On pr?sente l'actualit? de derni?re heure en temps r?el, les nouvelles r?gionales, internationales et ?conomiques, et plus encore.</desc>
    <image>http://dshm.tmsimg.com/assets/p7842532_b_h8_aa.jpg</image>
    <start>03:00AM</start>
    <finish>03:35AM</finish>
    <date>14 May 2025</date>
  </channel>
  <channel>
    <name>TVA CA</name>
    <title>? vos affaires</title>
    <desc>Simon Philibert d?cortique l'actualit? ?conomique et ses impacts dans le quotidien des Qu?b?cois.</desc>
    <image>http://dshm.tmsimg.com/assets/p19324420_b_h8_ab.jpg</image>
    <start>03:35AM</start>
    <finish>04:05AM</finish>
    <date>14 May 2025</date>
  </channel>
  <channel>
    <name>TVA CA</name>
    <title>30 jours max</title>
    <desc>Rayane, un policier peureux et maladroit dont les coll?gues se moquent toujours, apprend par son m?decin qu'il ne lui reste que 30 jours ? vivre. Devant cette nouvelle, il comprend que c'est l? sa derni?re chance de devenir le h?ros qu'il a toujours voulu ?tre au sein de son commissariat et ainsi impressionner sa coll?gue St?phanie. Le v?ritable ?tre craintif qu'il ?tait se transforme alors en policier pr?t ? prendre des risques pour attraper le grand baron de la drogue.</desc>
    <image>http://dshm.tmsimg.com/assets/p18106539_v_h10_aa.jpg</image>
    <start>04:05AM</start>
    <finish>05:50AM</finish>
    <date>14 May 2025</date>
  </channel>
  <channel>
    <name>TVA CA</name>
    <title>10 jours sans maman</title>
    <desc>Antoine est en passe d'obtenir une grosse promotion. C'est le moment que choisit sa femme, Isabelle, pour faire une pause et prendre l'air quelques jours pour s'occuper d'elle. Antoine se retrouve alors seul ? devoir g?rer la maison et leurs quatre enfants. Il est vite d?pass? par les ?v?nements.</desc>
    <image>http://dshm.tmsimg.com/assets/p16928178_v_h10_ah.jpg</image>
    <start>05:50AM</start>
    <finish>07:38AM</finish>
    <date>14 May 2025</date>
  </channel>
  <channel>
    <name>TVA CA</name>
    <title>Infopublicit?</title>
    <desc>Ceci est une ?mission publicitaire pay?e.</desc>
    <image>http://dshm.tmsimg.com/assets/p407792_b_h8_aa.jpg</image>
    <start>07:38AM</start>
    <finish>08:08AM</finish>
    <date>14 May 2025</date>
  </channel>
  <channel>
    <name>TVA CA</name>
    <title>Infopublicit?</title>
    <desc>Ceci est une ?mission publicitaire pay?e.</desc>
    <image>http://dshm.tmsimg.com/assets/p407792_b_h8_aa.jpg</image>
    <start>08:08AM</start>
    <finish>08:38AM</finish>
    <date>14 May 2025</date>
  </channel>
  <channel>
    <name>TVA CA</name>
    <title>Infopublicit?</title>
    <desc>Ceci est une ?mission publicitaire pay?e.</desc>
    <image>http://dshm.tmsimg.com/assets/p407792_b_h8_aa.jpg</image>
    <start>08:38AM</start>
    <finish>09:08AM</finish>
    <date>14 May 2025</date>
  </channel>
  <channel>
    <name>TVA CA</name>
    <title>TVA nouvelles</title>
    <desc>Information r?gionale, nationale et internationale.</desc>
    <image>http://dshm.tmsimg.com/assets/p15219361_b_h8_af.jpg</image>
    <start>09:08AM</start>
    <finish>10:00AM</finish>
    <date>14 May 2025</date>
  </channel>
  <channel>
    <name>TVA CA</name>
    <title>La victoire de l'amour</title>
    <desc>Pr?sent?e par l'organisme catholique La Victoire de l'amour, cette ?mission religieuse du m?me nom est constitu?e de t?moignages de personnes qui sont parvenues, gr?ce ? leur foi, ? surmonter de lourdes ?preuves. Les invit?s font preuve de courage et sont une source d'inspiration.</desc>
    <image>http://dshm.tmsimg.com/assets/p16109298_b_h10_aa.jpg</image>
    <start>10:00AM</start>
    <finish>10:15AM</finish>
    <date>14 May 2025</date>
  </channel>
  <channel>
    <name>TVA CA</name>
    <title>La victoire de l'amour</title>
    <desc>Pr?sent?e par l'organisme catholique La Victoire de l'amour, cette ?mission religieuse du m?me nom est constitu?e de t?moignages de personnes qui sont parvenues, gr?ce ? leur foi, ? surmonter de lourdes ?preuves. Les invit?s font preuve de courage et sont une source d'inspiration.</desc>
    <image>http://dshm.tmsimg.com/assets/p16109298_b_h10_aa.jpg</image>
    <start>10:15AM</start>
    <finish>10:30AM</finish>
    <date>14 May 2025</date>
  </channel>
  <channel>
    <name>TVA CA</name>
    <title>Le Qu?bec matin</title>
    <desc>On reste ? l'aff?t de toute l'actualit? sur des sujets tels que la politique, l'?conomie, la sant?, la m?t?o et la consommation gr?ce ? des reporters en direct sur le terrain ? Montr?al, Qu?bec, Sherbrooke, Trois-Rivi?res, Saguenay et Rimouski.</desc>
    <image>http://dshm.tmsimg.com/assets/p11006847_b_h8_aa.jpg</image>
    <start>10:30AM</start>
    <finish>11:30AM</finish>
    <date>14 May 2025</date>
  </channel>
  <channel>
    <name>TVA CA</name>
    <title>Salut bonjour</title>
    <desc>Actualit?, revue de presse, m?t?o, circulation, actualit?s culturelles et sportives sont abord?es avec dynamisme et enthousiasme chaque matin. Diff?rents collaborateurs viennent partager leurs passions: cuisine, sant?, famille, mode, etc.</desc>
    <image>http://dshm.tmsimg.com/assets/p28150848_b_h8_aa.jpg</image>
    <start>11:30AM</start>
    <finish>03:29PM</finish>
    <date>14 May 2025</date>
  </channel>
  <channel>
    <name>TVA CA</name>
    <title>Le tricheur</title>
    <desc>Rosalie Vaillancourt, Gino Chouinard, Jeff Boudreau, Brigitte Lafleur, Sonia Vachon.</desc>
    <image>http://dshm.tmsimg.com/assets/p28151111_b_h8_aa.jpg</image>
    <start>03:29PM</start>
    <finish>03:59PM</finish>
    <date>14 May 2025</date>
  </channel>
  <channel>
    <name>TVA CA</name>
    <title>Mario Dumont</title>
    <desc>Mario Dumont d?cortique les grands titres de l'actualit? et s'int?resse ? ce qui touche les Qu?b?cois, tels que la sant?, les finances personnelles et les nouvelles politiques.</desc>
    <image>http://dshm.tmsimg.com/assets/p9426305_b_h8_ad.jpg</image>
    <start>03:59PM</start>
    <finish>04:58PM</finish>
    <date>14 May 2025</date>
  </channel>
  <channel>
    <name>TVA CA</name>
    <title>TVA nouvelles</title>
    <desc>Avec Julie Marcoux, on reste au fait des nouvelles de derni?re heure, des analyses, du sport et la m?t?o dans un bulletin d'information complet.</desc>
    <image>http://dshm.tmsimg.com/assets/p9490084_b_h8_af.jpg</image>
    <start>04:58PM</start>
    <finish>06:00PM</finish>
    <date>14 May 2025</date>
  </channel>
  <channel>
    <name>TVA CA</name>
    <title>Belle-fille</title>
    <desc>Lorsque Louise d?couvre que son mari la trompe, elle d?cide de partir en Corse pour d?compresser le temps d'un weekend. Elle y rencontre un bel ?tranger et passe une nuit avec celui-ci. Au cours de ce weekend, elle devient malgr? elle la belle-fille de la m?re de son amant.</desc>
    <image>http://dshm.tmsimg.com/assets/p17557023_v_h8_ah.jpg</image>
    <start>06:00PM</start>
    <finish>08:00PM</finish>
    <date>14 May 2025</date>
  </channel>
  <channel>
    <name>TVA CA</name>
    <title>Infopublicit?</title>
    <desc>Ceci est une ?mission publicitaire pay?e.</desc>
    <image>http://dshm.tmsimg.com/assets/p407792_b_h8_aa.jpg</image>
    <start>08:00PM</start>
    <finish>08:30PM</finish>
    <date>14 May 2025</date>
  </channel>
  <channel>
    <name>TVA CA</name>
    <title>Les feux de l'amour</title>
    <desc>La relation entre Sharon et Scott se r?chauffe; Nick d?fend Victoria; Abby se jette dans le march? des rencontres.</desc>
    <image>http://dshm.tmsimg.com/assets/p183904_b_h10_ak.jpg</image>
    <start>08:30PM</start>
    <finish>09:28PM</finish>
    <date>14 May 2025</date>
  </channel>
  <channel>
    <name>TVA CA</name>
    <title>Top mod?les</title>
    <desc>Li et Finn sont stup?faits par les r?sultats de l'autopsie de Hollis.</desc>
    <image>http://dshm.tmsimg.com/assets/p183907_b_h10_ab.jpg</image>
    <start>09:28PM</start>
    <finish>09:58PM</finish>
    <date>14 May 2025</date>
  </channel>
  <channel>
    <name>TVA CA</name>
    <title>TVA nouvelles</title>
    <desc>Avec Sophie Thibault, on est au fait des nouvelles de derni?re heure, des analyses, du sport et de la m?t?o au bulletin d'information compl?te et pr?f?r? des Qu?b?cois.</desc>
    <image>http://dshm.tmsimg.com/assets/p9490107_b_h8_ae.jpg</image>
    <start>09:58PM</start>
    <finish>10:58PM</finish>
    <date>14 May 2025</date>
  </channel>
  <channel>
    <name>TVA CA</name>
    <title>TVA nouvelles</title>
    <desc>Avec Sophie Thibault, on est au fait des nouvelles de derni?re heure, des analyses, du sport et de la m?t?o au bulletin d'information compl?te et pr?f?r? des Qu?b?cois.</desc>
    <image>http://dshm.tmsimg.com/assets/p9490107_b_h8_ae.jpg</image>
    <start>10:58PM</start>
    <finish>11:29PM</finish>
    <date>14 May 2025</date>
  </channel>
  <channel>
    <name>TVA CA</name>
    <title>Le tricheur</title>
    <desc>Anne Grenier, Alain Dumas, F?lix-Antoine Tremblay, Dave Morissette, Anick Dumontet.</desc>
    <image>http://dshm.tmsimg.com/assets/p9000285_b_h8_aa.jpg</image>
    <start>11:29PM</start>
    <finish>11:59PM</finish>
    <date>14 May 2025</date>
  </channel>
  <channel>
    <name>TVA CA</name>
    <title>Masterchef Junior Qu?bec</title>
    <desc>Les candidats s'activent en cuisine afin de d?payser le jury avec leurs cr?ations; le temps file et les ?quipes tentent de n'oublier aucun d?tail; l'heure de la d?gustation approche et tous ont h?te de pr?senter leurs assiettes cuisin?es en commun.</desc>
    <image>http://dshm.tmsimg.com/assets/p29920131_b_h8_ab.jpg</image>
    <start>11:59PM</start>
    <finish>12:30AM</finish>
    <date>14 May 2025</date>
  </channel>
  <channel>
    <name>TVA CA</name>
    <title>Le vrai du faux</title>
    <desc>Invention insolite: des jeans anti-craque pour les plombiers, est-ce cr?dible; un massage avec des serpents venimeux, histoire invent?e de toutes pi?ces; Mario Tessier re?oit Mathieu Dufour, Tammy Verge, Debbie Lynch-White et Christian B?gin.</desc>
    <image>http://dshm.tmsimg.com/assets/p29751621_b_h10_ab.jpg</image>
    <start>12:30AM</start>
    <finish>01:00AM</finish>
    <date>15 May 2025</date>
  </channel>
</tv>
