<?xml version="1.0" ?>
<tv>
  <channel>
    <name>BBC One NL</name>
    <title>Countryfile</title>
    <desc>Adam Henson is in Somerset to meet the Baker family - three generations on a small, mixed farm, juggling cattle, crops and rare-breed pigs. As Adam mucks in, he gets an insight into the family's highs, lows and changing roles across the generations.</desc>
    <image>https://staticqbr-nl-prod.prod.cdn.dmdsdp.com/image-service/ImagesEPG/EventImages/p8094966_bd_h10_ab.jpg</image>
    <start>07:15PM</start>
    <finish>08:15PM</finish>
    <date>20 July 2025</date>
  </channel>
</tv>
