<?xml version="1.0" ?>
<tv>
  <channel>
    <name>TF 1 FR</name>
    <title>Camping Paradis</title>
    <desc>L?a, encore mineure, et son petit ami, Thibault, attendent un enfant. Ils esp?rent que les parents de L?a se montreront bienveillants ? leur ?gard. Quant ? Xavier, il ?prouve de tendres sentiments pour B?rang?re, la soeur de Christian..</desc>
    <image>https://thumb.canalplus.pro/http/unsafe/{resolutionXY}/filters:quality({imageQualityPercentage})/img-hapi.canalplus.pro:80/ServiceImage/ImageID/111423881</image>
    <start>03:55PM</start>
    <finish>05:00PM</finish>
    <date>05 August 2025</date>
  </channel>
</tv>
