<?xml version="1.0" ?>
<tv>
  <channel>
    <name>TF 1 FR</name>
    <title>Les secrets d'une nounou de star</title>
    <desc>Gaby, jeune romanci?re en devenir, est contact?e par Justice Gray, une chanteuse mondialement connue, pour s'occuper de sa fille ?g?e de 13 ans. La jeune femme s'aper?oit vite que Justice est menac?e et que le danger r?de autour de sa famille. Mais d'o? vient cette menace, d'un fan ou de son entourage ?..</desc>
    <image>https://thumb.canalplus.pro/http/unsafe/{resolutionXY}/filters:quality({imageQualityPercentage})/media.prod.hawc.canal.aws.io-cplus.net/ab56d7677a146ae1d8d9660f73a94365.jpg</image>
    <start>03:00PM</start>
    <finish>04:30PM</finish>
    <date>22 May 2025</date>
  </channel>
</tv>
