<?xml version="1.0" ?>
<tv>
  <channel>
    <name>S4C UK</name>
    <id>S4C.uk</id>
    <title>Cymry ar Gynfas</title>
    <desc>Y tro hwn, bydd yr artist print a cholagraff Marian Haf yn mynd ati i greu portread o'r cerddor a'r gyflwynwraig Tara Bethan. Print and collagraph artist Marian Haf portrays Tara Bethan.</desc>
    <image>https://images.metadata.sky.com/pd-image/84cff5c5-c74c-397c-9510-c48b55fa9f98/16-9</image>
    <start>12:05PM</start>
    <finish>12:30PM</finish>
    <date>18 September 2025</date>
  </channel>
</tv>
