<?xml version="1.0" ?>
<tv>
  <channel>
    <name>Detroit Public TV US</name>
    <id>WTVS.us</id>
    <title>A Binding Truth</title>
    <desc>Two former high school classmates, one white and one Black, who shared the same last name, are reconnected decades later by a shocking discovery found in church records.</desc>
    <image>http://dshm.tmsimg.com/assets/p30949121_st_h10_aa.jpg</image>
    <start>04:00AM</start>
    <finish>05:00AM</finish>
    <date>17 October 2025</date>
  </channel>
</tv>
