<?xml version="1.0" ?>
<tv>
  <channel>
    <name>TVNZ 1 NZ</name>
    <title>Keeping Up Appearances: The Father Christmas Suit</title>
    <desc>Hyacinth is in the full Christmas spirit with 112 Christmas cards, and counting. She's also forced Richard to dress up as Father Christmas to distribute presents to the old folk.</desc>
    <image>https://commons.wikimedia.org/wiki/File:Image_not_available.png</image>
    <start>12:35AM</start>
    <finish>01:15AM</finish>
    <date>19 July 2025</date>
  </channel>
</tv>
